[
  {
    "code": "D730",
    "level": 3,
    "description": "Hipoesplenismo",
    "diagnostico": "Enfermedades del bazo",
    "code_2": "D73",
    "code_0": "D50-D89",
    "code_1": "D70-D77"
  },
  {
    "code": "D731",
    "level": 3,
    "description": "Hiperesplenismo",
    "diagnostico": "Enfermedades del bazo",
    "code_2": "D73",
    "code_0": "D50-D89",
    "code_1": "D70-D77"
  },
  {
    "code": "D732",
    "level": 3,
    "description": "Esplenomegalia congestiva cr\u00f3nica",
    "diagnostico": "Enfermedades del bazo",
    "code_2": "D73",
    "code_0": "D50-D89",
    "code_1": "D70-D77"
  },
  {
    "code": "D733",
    "level": 3,
    "description": "Absceso del bazo",
    "diagnostico": "Enfermedades del bazo",
    "code_2": "D73",
    "code_0": "D50-D89",
    "code_1": "D70-D77"
  },
  {
    "code": "D734",
    "level": 3,
    "description": "Quiste del bazo",
    "diagnostico": "Enfermedades del bazo",
    "code_2": "D73",
    "code_0": "D50-D89",
    "code_1": "D70-D77"
  },
  {
    "code": "D735",
    "level": 3,
    "description": "Infarto del bazo",
    "diagnostico": "Enfermedades del bazo",
    "code_2": "D73",
    "code_0": "D50-D89",
    "code_1": "D70-D77"
  },
  {
    "code": "D720",
    "level": 3,
    "description": "Anomal\u00edas gen\u00e9ticas de los leucocitos",
    "diagnostico": "Trastornos de los gl贸bulos blancos",
    "code_2": "D72",
    "code_0": "D50-D89",
    "code_1": "D70-D77"
  },
  {
    "code": "D721",
    "level": 3,
    "description": "Eosinofilia",
    "diagnostico": "Trastornos de los gl贸bulos blancos",
    "code_2": "D72",
    "code_0": "D50-D89",
    "code_1": "D70-D77"
  },
  {
    "code": "D728",
    "level": 3,
    "description": "Otros trastornos especificados de los leucocitos",
    "diagnostico": "Trastornos de los gl贸bulos blancos",
    "code_2": "D72",
    "code_0": "D50-D89",
    "code_1": "D70-D77"
  },
  {
    "code": "D729",
    "level": 3,
    "description": "Trastorno de los leucocitos, no especificado",
    "diagnostico": "Trastornos de los gl贸bulos blancos",
    "code_2": "D72",
    "code_0": "D50-D89",
    "code_1": "D70-D77"
  },
  {
    "code": "C81",
    "level": 3,
    "description": "Enfermedad de Hodgkin",
    "diagnostico": "Enfermedades malignas",
    "code_2": "C81-C96",
    "code_0": "C00-D49",
    "code_1": "C00-C97"
  },
  {
    "code": "C82",
    "level": 3,
    "description": "Linfoma no Hodgkin folicular [nodular]",
    "diagnostico": "Enfermedades malignas",
    "code_2": "C81-C96",
    "code_0": "C00-D49",
    "code_1": "C00-C97"
  },
  {
    "code": "C83",
    "level": 3,
    "description": "Linfoma no Hodgkin difuso",
    "diagnostico": "Enfermedades malignas",
    "code_2": "C81-C96",
    "code_0": "C00-D49",
    "code_1": "C00-C97"
  },
  {
    "code": "C76",
    "level": 3,
    "description": "Tumor maligno de otros sitios y de sitios mal definidos",
    "diagnostico": "Enfermedades malignas",
    "code_2": "C76-C80",
    "code_0": "C00-D49",
    "code_1": "C00-C97"
  },
  {
    "code": "C77",
    "level": 3,
    "description": "Tumor maligno secundario y el no especificado de los ganglios linf\u00e1ticos",
    "diagnostico": "Enfermedades malignas",
    "code_2": "C76-C80",
    "code_0": "C00-D49",
    "code_1": "C00-C97"
  },
  {
    "code": "C00-C14",
    "level": 3,
    "description": "y de la faringe",
    "diagnostico": "Enfermedades malignas",
    "code_2": "C00-C75",
    "code_0": "C00-D49",
    "code_1": "C00-C97"
  },
  {
    "code": "C15-C26",
    "level": 3,
    "description": "Tumores malignos de los \u00f3rganos digestivos",
    "diagnostico": "Enfermedades malignas",
    "code_2": "C00-C75",
    "code_0": "C00-D49",
    "code_1": "C00-C97"
  },
  {
    "code": "C30-C39",
    "level": 3,
    "description": "e intrator\u00e1cicos",
    "diagnostico": "Enfermedades malignas",
    "code_2": "C00-C75",
    "code_0": "C00-D49",
    "code_1": "C00-C97"
  },
  {
    "code": "C40-C41",
    "level": 3,
    "description": "Tumores malignos de los huesos y de los cart\u00edlagos articulares",
    "diagnostico": "Enfermedades malignas",
    "code_2": "C00-C75",
    "code_0": "C00-D49",
    "code_1": "C00-C97"
  },
  {
    "code": "C43-C44",
    "level": 3,
    "description": "Melanoma y otros tumores malignos de la piel",
    "diagnostico": "Enfermedades malignas",
    "code_2": "C00-C75",
    "code_0": "C00-D49",
    "code_1": "C00-C97"
  },
  {
    "code": "D060",
    "level": 3,
    "description": "Carcinoma in situ del endoc\u00e9rvix",
    "diagnostico": "Enfermedades del sistema circulatorio",
    "code_2": "D06",
    "code_0": "C00-D49",
    "code_1": "D00-D09"
  },
  {
    "code": "D061",
    "level": 3,
    "description": "Carcinoma in situ del exoc\u00e9rvix",
    "code_2": "D06",
    "code_0": "C00-D49",
    "code_1": "D00-D09"
  },
  {
    "code": "D067",
    "level": 3,
    "description": "Carcinoma in situ de otras partes especificadas del cuello del \u00fatero",
    "code_2": "D06",
    "code_0": "C00-D49",
    "code_1": "D00-D09"
  },
  {
    "code": "D069",
    "level": 3,
    "description": "Carcinoma in situ del cuello del \u00fatero, parte no especificada",
    "code_2": "D06",
    "code_0": "C00-D49",
    "code_1": "D00-D09"
  },
  {
    "code": "D050",
    "level": 3,
    "description": "Carcinoma in situ lobular",
    "code_2": "D05",
    "code_0": "C00-D49",
    "code_1": "D00-D09"
  },
  {
    "code": "D051",
    "level": 3,
    "description": "Carcinoma in situ intracanalicular",
    "code_2": "D05",
    "code_0": "C00-D49",
    "code_1": "D00-D09"
  },
  {
    "code": "D057",
    "level": 3,
    "description": "Otros carcinomas in situ de la mama",
    "code_2": "D05",
    "code_0": "C00-D49",
    "code_1": "D00-D09"
  },
  {
    "code": "D059",
    "level": 3,
    "description": "Carcinoma in situ de la mama, parte no especificada",
    "code_2": "D05",
    "code_0": "C00-D49",
    "code_1": "D00-D09"
  },
  {
    "code": "D040",
    "level": 3,
    "description": "Carcinoma in situ de la piel del labio",
    "code_2": "D04",
    "code_0": "C00-D49",
    "code_1": "D00-D09"
  },
  {
    "code": "D041",
    "level": 3,
    "description": "Carcinoma in situ de la piel del p\u00e1rpado y de la comisura palpebral",
    "code_2": "D04",
    "code_0": "C00-D49",
    "code_1": "D00-D09"
  },
  {
    "code": "D042",
    "level": 3,
    "description": "Carcinoma in situ de la piel de la oreja y del conducto auditivo externo",
    "code_2": "D04",
    "code_0": "C00-D49",
    "code_1": "D00-D09"
  },
  {
    "code": "D043",
    "level": 3,
    "description": "Carcinoma in situ de la piel de otras partes y de las no especificadas de la cara",
    "code_2": "D04",
    "code_0": "C00-D49",
    "code_1": "D00-D09"
  },
  {
    "code": "D044",
    "level": 3,
    "description": "Carcinoma in situ de la piel del cuero cabelludo y cuello",
    "code_2": "D04",
    "code_0": "C00-D49",
    "code_1": "D00-D09"
  },
  {
    "code": "D045",
    "level": 3,
    "description": "Carcinoma in situ de la piel del tronco",
    "code_2": "D04",
    "code_0": "C00-D49",
    "code_1": "D00-D09"
  },
  {
    "code": "D030",
    "level": 3,
    "description": "Melanoma in situ del labio",
    "code_2": "D03",
    "code_0": "C00-D49",
    "code_1": "D00-D09"
  },
  {
    "code": "D031",
    "level": 3,
    "description": "Melanoma in situ del p\u00e1rpado y de la comisura palpebral",
    "code_2": "D03",
    "code_0": "C00-D49",
    "code_1": "D00-D09"
  },
  {
    "code": "D032",
    "level": 3,
    "description": "Melanoma in situ de la oreja y del conducto auditivo externo",
    "code_2": "D03",
    "code_0": "C00-D49",
    "code_1": "D00-D09"
  },
  {
    "code": "D033",
    "level": 3,
    "description": "Melanoma in situ de otras partes y de las no especificadas de la cara",
    "code_2": "D03",
    "code_0": "C00-D49",
    "code_1": "D00-D09"
  },
  {
    "code": "D034",
    "level": 3,
    "description": "Melanoma in situ del cuero cabelludo y del cuello",
    "code_2": "D03",
    "code_0": "C00-D49",
    "code_1": "D00-D09"
  },
  {
    "code": "D035",
    "level": 3,
    "description": "Melanoma in situ del tronco",
    "code_2": "D03",
    "code_0": "C00-D49",
    "code_1": "D00-D09"
  },
  {
    "code": "D036",
    "level": 3,
    "description": "Melanoma in situ del miembro superior, incluido el hombro",
    "code_2": "D03",
    "code_0": "C00-D49",
    "code_1": "D00-D09"
  },
  {
    "code": "D037",
    "level": 3,
    "description": "Melanoma in situ del miembro inferior, incluida la cadera",
    "code_2": "D03",
    "code_0": "C00-D49",
    "code_1": "D00-D09"
  },
  {
    "code": "D038",
    "level": 3,
    "description": "Melanoma in situ de otros sitios",
    "code_2": "D03",
    "code_0": "C00-D49",
    "code_1": "D00-D09"
  },
  {
    "code": "D020",
    "level": 3,
    "description": "Carcinoma in situ de la laringe",
    "code_2": "D02",
    "code_0": "C00-D49",
    "code_1": "D00-D09"
  },
  {
    "code": "D021",
    "level": 3,
    "description": "Carcinoma in situ de la tr\u00e1quea",
    "code_2": "D02",
    "code_0": "C00-D49",
    "code_1": "D00-D09"
  },
  {
    "code": "D022",
    "level": 3,
    "description": "Carcinoma in situ del bronquio y del pulm\u00f3n",
    "code_2": "D02",
    "code_0": "C00-D49",
    "code_1": "D00-D09"
  },
  {
    "code": "D023",
    "level": 3,
    "description": "Carcinoma in situ de otras partes del sistema respiratorio",
    "code_2": "D02",
    "code_0": "C00-D49",
    "code_1": "D00-D09"
  },
  {
    "code": "D024",
    "level": 3,
    "description": "Carcinoma in situ de \u00f3rganos respiratorios no especificados",
    "code_2": "D02",
    "code_0": "C00-D49",
    "code_1": "D00-D09"
  },
  {
    "code": "D010",
    "level": 3,
    "description": "Carcinoma in situ del colon",
    "code_2": "D01",
    "code_0": "C00-D49",
    "code_1": "D00-D09"
  },
  {
    "code": "D011",
    "level": 3,
    "description": "Carcinoma in situ de la uni\u00f3n rectosigmoidea",
    "code_2": "D01",
    "code_0": "C00-D49",
    "code_1": "D00-D09"
  },
  {
    "code": "D012",
    "level": 3,
    "description": "Carcinoma in situ del recto",
    "code_2": "D01",
    "code_0": "C00-D49",
    "code_1": "D00-D09"
  },
  {
    "code": "D013",
    "level": 3,
    "description": "Carcinoma in situ del ano y del conducto anal",
    "code_2": "D01",
    "code_0": "C00-D49",
    "code_1": "D00-D09"
  },
  {
    "code": "D014",
    "level": 3,
    "description": "Carcinoma in situ de otras partes y de las no especificadas del intestino",
    "code_2": "D01",
    "code_0": "C00-D49",
    "code_1": "D00-D09"
  },
  {
    "code": "D000",
    "level": 3,
    "description": "Carcinoma in situ del labio, de la cavidad bucal y de la faringe",
    "code_2": "D00",
    "code_0": "C00-D49",
    "code_1": "D00-D09"
  },
  {
    "code": "D001",
    "level": 3,
    "description": "Carcinoma in situ del es\u00f3fago",
    "code_2": "D00",
    "code_0": "C00-D49",
    "code_1": "D00-D09"
  },
  {
    "code": "D002",
    "level": 3,
    "description": "Carcinoma in situ del est\u00f3mago",
    "code_2": "D00",
    "code_0": "C00-D49",
    "code_1": "D00-D09"
  },
  {
    "code": "D120",
    "level": 3,
    "description": "Tumor benigno del ciego",
    "code_2": "D12",
    "code_0": "C00-D49",
    "code_1": "D10-D36"
  },
  {
    "code": "D121",
    "level": 3,
    "description": "Tumor benigno del ap\u00e9ndice",
    "code_2": "D12",
    "code_0": "C00-D49",
    "code_1": "D10-D36"
  },
  {
    "code": "D122",
    "level": 3,
    "description": "Tumor benigno del colon ascendente",
    "code_2": "D12",
    "code_0": "C00-D49",
    "code_1": "D10-D36"
  },
  {
    "code": "D123",
    "level": 3,
    "description": "Tumor benigno del colon transverso",
    "code_2": "D12",
    "code_0": "C00-D49",
    "code_1": "D10-D36"
  },
  {
    "code": "D124",
    "level": 3,
    "description": "Tumor benigno del colon descendente",
    "code_2": "D12",
    "code_0": "C00-D49",
    "code_1": "D10-D36"
  },
  {
    "code": "D125",
    "level": 3,
    "description": "Tumor benigno del colon sigmoide",
    "code_2": "D12",
    "code_0": "C00-D49",
    "code_1": "D10-D36"
  },
  {
    "code": "D126",
    "level": 3,
    "description": "Tumor benigno del colon, parte no especificada",
    "code_2": "D12",
    "code_0": "C00-D49",
    "code_1": "D10-D36"
  },
  {
    "code": "D127",
    "level": 3,
    "description": "Tumor benigno de la uni\u00f3n rectosigmoidea",
    "code_2": "D12",
    "code_0": "C00-D49",
    "code_1": "D10-D36"
  },
  {
    "code": "D110",
    "level": 3,
    "description": "Tumor benigno de la gl\u00e1ndula par\u00f3tida",
    "code_2": "D11",
    "code_0": "C00-D49",
    "code_1": "D10-D36"
  },
  {
    "code": "D117",
    "level": 3,
    "description": "Tumor benigno de otras gl\u00e1ndulas salivales mayores especificadas",
    "code_2": "D11",
    "code_0": "C00-D49",
    "code_1": "D10-D36"
  },
  {
    "code": "D119",
    "level": 3,
    "description": "Tumor benigno de la gl\u00e1ndula salival mayor, sin otra especificaci\u00f3n",
    "code_2": "D11",
    "code_0": "C00-D49",
    "code_1": "D10-D36"
  },
  {
    "code": "D100",
    "level": 3,
    "description": "Tumor benigno del labio",
    "code_2": "D10",
    "code_0": "C00-D49",
    "code_1": "D10-D36"
  },
  {
    "code": "D101",
    "level": 3,
    "description": "Tumor benigno de la lengua",
    "code_2": "D10",
    "code_0": "C00-D49",
    "code_1": "D10-D36"
  },
  {
    "code": "D102",
    "level": 3,
    "description": "Tumor benigno del piso de la boca",
    "code_2": "D10",
    "code_0": "C00-D49",
    "code_1": "D10-D36"
  },
  {
    "code": "D103",
    "level": 3,
    "description": "Tumor benigno de otras partes y de las no especificadas de la boca",
    "code_2": "D10",
    "code_0": "C00-D49",
    "code_1": "D10-D36"
  },
  {
    "code": "D104",
    "level": 3,
    "description": "Tumor benigno de la am\u00edgdala",
    "code_2": "D10",
    "code_0": "C00-D49",
    "code_1": "D10-D36"
  },
  {
    "code": "D105",
    "level": 3,
    "description": "Tumor benigno de otras partes de la orofaringe",
    "code_2": "D10",
    "code_0": "C00-D49",
    "code_1": "D10-D36"
  },
  {
    "code": "D106",
    "level": 3,
    "description": "Tumor benigno de la nasofaringe",
    "code_2": "D10",
    "code_0": "C00-D49",
    "code_1": "D10-D36"
  },
  {
    "code": "D107",
    "level": 3,
    "description": "Tumor benigno de la hipofaringe",
    "code_2": "D10",
    "code_0": "C00-D49",
    "code_1": "D10-D36"
  },
  {
    "code": "D109",
    "level": 3,
    "description": "Tumor benigno de la faringe, parte no especificada",
    "code_2": "D10",
    "code_0": "C00-D49",
    "code_1": "D10-D36"
  },
  {
    "code": "D420",
    "level": 3,
    "description": "Tumor de comportamiento incierto o desconocido de las meninges cerebrales",
    "code_2": "D42",
    "code_0": "C00-D49",
    "code_1": "D37-D48"
  },
  {
    "code": "D421",
    "level": 3,
    "description": "Tumor de comportamiento incierto o desconocido de las meninges raqu\u00eddeas",
    "code_2": "D42",
    "code_0": "C00-D49",
    "code_1": "D37-D48"
  },
  {
    "code": "D429",
    "level": 3,
    "description": "Tumor de comportamiento incierto o desconocido de las meninges, parte no especificada",
    "code_2": "D42",
    "code_0": "C00-D49",
    "code_1": "D37-D48"
  },
  {
    "code": "D410",
    "level": 3,
    "description": "Tumor de comportamiento incierto o desconocido del ri\u00f1\u00f3n",
    "code_2": "D41",
    "code_0": "C00-D49",
    "code_1": "D37-D48"
  },
  {
    "code": "D411",
    "level": 3,
    "description": "Tumor de comportamiento incierto o desconocido de la pelvis renal",
    "code_2": "D41",
    "code_0": "C00-D49",
    "code_1": "D37-D48"
  },
  {
    "code": "D412",
    "level": 3,
    "description": "Tumor de comportamiento incierto o desconocido del ur\u00e9ter",
    "code_2": "D41",
    "code_0": "C00-D49",
    "code_1": "D37-D48"
  },
  {
    "code": "D413",
    "level": 3,
    "description": "Tumor de comportamiento incierto o desconocido de la uretra",
    "code_2": "D41",
    "code_0": "C00-D49",
    "code_1": "D37-D48"
  },
  {
    "code": "D414",
    "level": 3,
    "description": "Tumor de comportamiento incierto o desconocido de la vejiga",
    "code_2": "D41",
    "code_0": "C00-D49",
    "code_1": "D37-D48"
  },
  {
    "code": "D417",
    "level": 3,
    "description": "Tumor de comportamiento incierto o desconocido de otros \u00f3rganos urinarios",
    "code_2": "D41",
    "code_0": "C00-D49",
    "code_1": "D37-D48"
  },
  {
    "code": "D419",
    "level": 3,
    "description": "Tumor de comportamiento incierto o desconocido de \u00f3rgano urinario no especificado",
    "code_2": "D41",
    "code_0": "C00-D49",
    "code_1": "D37-D48"
  },
  {
    "code": "D400",
    "level": 3,
    "description": "Tumor de comportamiento incierto o desconocido de la pr\u00f3stata",
    "code_2": "D40",
    "code_0": "C00-D49",
    "code_1": "D37-D48"
  },
  {
    "code": "D401",
    "level": 3,
    "description": "Tumor de comportamiento incierto o desconocido del test\u00edculo",
    "code_2": "D40",
    "code_0": "C00-D49",
    "code_1": "D37-D48"
  },
  {
    "code": "D407",
    "level": 3,
    "description": "Tumor de comportamiento incierto o desconocido de otros \u00f3rganos genitales masculinos",
    "code_2": "D40",
    "code_0": "C00-D49",
    "code_1": "D37-D48"
  },
  {
    "code": "D409",
    "level": 3,
    "description": "Tumor de comportamiento incierto o desconocido de \u00f3rgano genital masculino no especificado",
    "code_2": "D40",
    "code_0": "C00-D49",
    "code_1": "D37-D48"
  },
  {
    "code": "D390",
    "level": 3,
    "description": "Tumor de comportamiento incierto o desconocido del \u00fatero",
    "code_2": "D39",
    "code_0": "C00-D49",
    "code_1": "D37-D48"
  },
  {
    "code": "D391",
    "level": 3,
    "description": "Tumor de comportamiento incierto o desconocido del ovario",
    "code_2": "D39",
    "code_0": "C00-D49",
    "code_1": "D37-D48"
  },
  {
    "code": "D392",
    "level": 3,
    "description": "Tumor de comportamiento incierto o desconocido de la placenta",
    "code_2": "D39",
    "code_0": "C00-D49",
    "code_1": "D37-D48"
  },
  {
    "code": "D397",
    "level": 3,
    "description": "Tumor de comportamiento incierto o desconocido de otros \u00f3rganos genitales femeninos",
    "code_2": "D39",
    "code_0": "C00-D49",
    "code_1": "D37-D48"
  },
  {
    "code": "D399",
    "level": 3,
    "description": "Tumor de comportamiento incierto o desconocido de \u00f3rgano genital femenino no especificado",
    "code_2": "D39",
    "code_0": "C00-D49",
    "code_1": "D37-D48"
  },
  {
    "code": "D380",
    "level": 3,
    "description": "Tumor de comportamiento incierto o desconocido de laringe",
    "code_2": "D38",
    "code_0": "C00-D49",
    "code_1": "D37-D48"
  },
  {
    "code": "D381",
    "level": 3,
    "description": "Tumor de comportamiento incierto o desconocido de la tr\u00e1quea, de los bronquios y del pulm\u00f3n",
    "code_2": "D38",
    "code_0": "C00-D49",
    "code_1": "D37-D48"
  },
  {
    "code": "D382",
    "level": 3,
    "description": "Tumor de comportamiento incierto o desconocido de la pleura",
    "code_2": "D38",
    "code_0": "C00-D49",
    "code_1": "D37-D48"
  },
  {
    "code": "D370",
    "level": 3,
    "description": "Tumor de comportamiento incierto o desconocido del labio, de la cavidad bucal y de la faringe",
    "code_2": "D37",
    "code_0": "C00-D49",
    "code_1": "D37-D48"
  },
  {
    "code": "D371",
    "level": 3,
    "description": "Tumor de comportamiento incierto o desconocido del est\u00f3mago",
    "code_2": "D37",
    "code_0": "C00-D49",
    "code_1": "D37-D48"
  },
  {
    "code": "D372",
    "level": 3,
    "description": "Tumor de comportamiento incierto o desconocido del intestino delgado",
    "code_2": "D37",
    "code_0": "C00-D49",
    "code_1": "D37-D48"
  },
  {
    "code": "D373",
    "level": 3,
    "description": "Tumor de comportamiento incierto o desconocido del ap\u00e9ndice",
    "code_2": "D37",
    "code_0": "C00-D49",
    "code_1": "D37-D48"
  },
  {
    "code": "D374",
    "level": 3,
    "description": "Tumor de comportamiento incierto o desconocido del colon",
    "code_2": "D37",
    "code_0": "C00-D49",
    "code_1": "D37-D48"
  },
  {
    "code": "D375",
    "level": 3,
    "description": "Tumor de comportamiento incierto o desconocido del recto",
    "code_2": "D37",
    "code_0": "C00-D49",
    "code_1": "D37-D48"
  },
  {
    "code": "D376",
    "level": 3,
    "description": "Tumor de comportamiento incierto o desconocido del h\u00edgado, de la ves\u00edcula biliar y del conducto biliar",
    "code_2": "D37",
    "code_0": "C00-D49",
    "code_1": "D37-D48"
  },
  {
    "code": "D377",
    "level": 3,
    "description": "Tumor de comportamiento incierto o desconocido de otros \u00f3rganos digestivos especificados",
    "code_2": "D37",
    "code_0": "C00-D49",
    "code_1": "D37-D48"
  },
  {
    "code": "G320",
    "level": 3,
    "description": "Degeneraci\u00f3n combinada subaguda de la m\u00e9dula espinal en enfermedades clasificadas en otra parte",
    "code_2": "G32",
    "code_0": "G00-G99",
    "code_1": "G30-G32"
  },
  {
    "code": "G328",
    "level": 3,
    "description": "Otros trastornos degenerativos especificados del sistema nervioso en enfermedades clasificadas en otra parte",
    "code_2": "G32",
    "code_0": "G00-G99",
    "code_1": "G30-G32"
  },
  {
    "code": "G310",
    "level": 3,
    "description": "Atrofia cerebral circunscrita",
    "code_2": "G31",
    "code_0": "G00-G99",
    "code_1": "G30-G32"
  },
  {
    "code": "G311",
    "level": 3,
    "description": "Degeneraci\u00f3n cerebral senil no clasificada en otra parte",
    "code_2": "G31",
    "code_0": "G00-G99",
    "code_1": "G30-G32"
  },
  {
    "code": "G312",
    "level": 3,
    "description": "Degeneraci\u00f3n del sistema nervioso debida al alcohol",
    "code_2": "G31",
    "code_0": "G00-G99",
    "code_1": "G30-G32"
  },
  {
    "code": "G318",
    "level": 3,
    "description": "Otras enfermedades degenerativas especificadas del sistema nervioso",
    "code_2": "G31",
    "code_0": "G00-G99",
    "code_1": "G30-G32"
  },
  {
    "code": "G319",
    "level": 3,
    "description": "Degeneraci\u00f3n del sistema nervioso, no especificada",
    "code_2": "G31",
    "code_0": "G00-G99",
    "code_1": "G30-G32"
  },
  {
    "code": "G300",
    "level": 3,
    "description": "Enfermedad de Alzheimer de comienzo temprano",
    "code_2": "G30",
    "code_0": "G00-G99",
    "code_1": "G30-G32"
  },
  {
    "code": "G301",
    "level": 3,
    "description": "Enfermedad de Alzheimer de comienzo tard\u00edo",
    "code_2": "G30",
    "code_0": "G00-G99",
    "code_1": "G30-G32"
  },
  {
    "code": "G308",
    "level": 3,
    "description": "Otros tipos de enfermedad de Alzheimer",
    "code_2": "G30",
    "code_0": "G00-G99",
    "code_1": "G30-G32"
  },
  {
    "code": "G309",
    "level": 3,
    "description": "Enfermedad de Alzheimer, no especificada",
    "code_2": "G30",
    "code_0": "G00-G99",
    "code_1": "G30-G32"
  },
  {
    "code": "M815",
    "level": 4,
    "description": "Osteoporosis idiop\u00e1tica, sin fractura patol\u00f3gica",
    "code_3": "M81",
    "code_0": "M00-M99",
    "code_1": "M80-M94",
    "code_2": "M80-M85"
  },
  {
    "code": "M816",
    "level": 4,
    "description": "Osteoporosis localizada [Lequesne], sin fractura patol\u00f3gica",
    "code_3": "M81",
    "code_0": "M00-M99",
    "code_1": "M80-M94",
    "code_2": "M80-M85"
  },
  {
    "code": "M818",
    "level": 4,
    "description": "Otras osteoporosis, sin fractura patol\u00f3gica",
    "code_3": "M81",
    "code_0": "M00-M99",
    "code_1": "M80-M94",
    "code_2": "M80-M85"
  },
  {
    "code": "M819",
    "level": 4,
    "description": "Osteoporosis no especificada, sin fractura patol\u00f3gica",
    "code_3": "M81",
    "code_0": "M00-M99",
    "code_1": "M80-M94",
    "code_2": "M80-M85"
  },
  {
    "code": "G370",
    "level": 3,
    "description": "Esclerosis difusa",
    "code_2": "G37",
    "code_0": "G00-G99",
    "code_1": "G35-G37"
  },
  {
    "code": "G371",
    "level": 3,
    "description": "Desmielinizaci\u00f3n central del cuerpo calloso",
    "code_2": "G37",
    "code_0": "G00-G99",
    "code_1": "G35-G37"
  },
  {
    "code": "G372",
    "level": 3,
    "description": "Mielin\u00f3lisis central pontina",
    "code_2": "G37",
    "code_0": "G00-G99",
    "code_1": "G35-G37"
  },
  {
    "code": "G373",
    "level": 3,
    "description": "Mielitis transversa aguda en enfermedad desmielinizante del sistema nervioso central",
    "code_2": "G37",
    "code_0": "G00-G99",
    "code_1": "G35-G37"
  },
  {
    "code": "G374",
    "level": 3,
    "description": "Mielitis necrotizante subaguda",
    "code_2": "G37",
    "code_0": "G00-G99",
    "code_1": "G35-G37"
  },
  {
    "code": "G375",
    "level": 3,
    "description": "Esclerosis conc\u00e9ntrica [Bal\u00f3]",
    "code_2": "G37",
    "code_0": "G00-G99",
    "code_1": "G35-G37"
  },
  {
    "code": "G378",
    "level": 3,
    "description": "Otras enfermedades desmielinizantes del sistema nervioso central, especificadas",
    "code_2": "G37",
    "code_0": "G00-G99",
    "code_1": "G35-G37"
  },
  {
    "code": "G379",
    "level": 3,
    "description": "Enfermedad desmielinizante del sistema nervioso central, no especificada",
    "code_2": "G37",
    "code_0": "G00-G99",
    "code_1": "G35-G37"
  },
  {
    "code": "M896",
    "level": 4,
    "description": "Osteopat\u00eda a consecuencia de poliomielitis",
    "code_3": "M89",
    "code_0": "M00-M99",
    "code_1": "M80-M94",
    "code_2": "M86-M90"
  },
  {
    "code": "M898",
    "level": 4,
    "description": "Otros trastornos especificados del hueso",
    "code_3": "M89",
    "code_0": "M00-M99",
    "code_1": "M80-M94",
    "code_2": "M86-M90"
  },
  {
    "code": "M899",
    "level": 4,
    "description": "Trastorno del hueso, no especificado",
    "code_3": "M89",
    "code_0": "M00-M99",
    "code_1": "M80-M94",
    "code_2": "M86-M90"
  },
  {
    "code": "M879",
    "level": 4,
    "description": "Osteonecrosis, no especificada",
    "code_3": "M87",
    "code_0": "M00-M99",
    "code_1": "M80-M94",
    "code_2": "M86-M90"
  },
  {
    "code": "G360",
    "level": 3,
    "description": "Neuromielitis \u00f3ptica [Devic]",
    "code_2": "G36",
    "code_0": "G00-G99",
    "code_1": "G35-G37"
  },
  {
    "code": "G361",
    "level": 3,
    "description": "Leucoencefalitis hemorr\u00e1gica aguda y subaguda [Hurst]",
    "code_2": "G36",
    "code_0": "G00-G99",
    "code_1": "G35-G37"
  },
  {
    "code": "G368",
    "level": 3,
    "description": "Otras desmielinizaciones agudas diseminadas especificadas",
    "code_2": "G36",
    "code_0": "G00-G99",
    "code_1": "G35-G37"
  },
  {
    "code": "G369",
    "level": 3,
    "description": "Desmielinizaci\u00f3n diseminada aguda, sin otra especificaci\u00f3n",
    "code_2": "G36",
    "code_0": "G00-G99",
    "code_1": "G35-G37"
  },
  {
    "code": "M864",
    "level": 4,
    "description": "Osteomielitis cr\u00f3nica con drenaje del seno",
    "code_3": "M86",
    "code_0": "M00-M99",
    "code_1": "M80-M94",
    "code_2": "M86-M90"
  },
  {
    "code": "M865",
    "level": 4,
    "description": "Otras osteomielitis hemat\u00f3genas cr\u00f3nicas",
    "code_3": "M86",
    "code_0": "M00-M99",
    "code_1": "M80-M94",
    "code_2": "M86-M90"
  },
  {
    "code": "M866",
    "level": 4,
    "description": "Otras osteomielitis cr\u00f3nicas",
    "code_3": "M86",
    "code_0": "M00-M99",
    "code_1": "M80-M94",
    "code_2": "M86-M90"
  },
  {
    "code": "M868",
    "level": 4,
    "description": "Otras osteomielitis",
    "code_3": "M86",
    "code_0": "M00-M99",
    "code_1": "M80-M94",
    "code_2": "M86-M90"
  },
  {
    "code": "M869",
    "level": 4,
    "description": "Osteomielitis, no especificada",
    "code_3": "M86",
    "code_0": "M00-M99",
    "code_1": "M80-M94",
    "code_2": "M86-M90"
  },
  {
    "code": "M626",
    "level": 4,
    "description": "Distensi\u00f3n muscular",
    "code_3": "M62",
    "code_0": "M00-M99",
    "code_1": "M60-M79",
    "code_2": "M60-M63"
  },
  {
    "code": "M628",
    "level": 4,
    "description": "Otros trastornos especificados de los m\u00fasculos",
    "code_3": "M62",
    "code_0": "M00-M99",
    "code_1": "M60-M79",
    "code_2": "M60-M63"
  },
  {
    "code": "M629",
    "level": 4,
    "description": "Trastorno muscular, no especificado",
    "code_3": "M62",
    "code_0": "M00-M99",
    "code_1": "M60-M79",
    "code_2": "M60-M63"
  },
  {
    "code": "M609",
    "level": 4,
    "description": "Miositis, no especificada",
    "code_3": "M60",
    "code_0": "M00-M99",
    "code_1": "M60-M79",
    "code_2": "M60-M63"
  },
  {
    "code": "H220",
    "level": 3,
    "description": "Iridociclitis en enfermedades infecciosas y parasitarias clasificadas en otra parte",
    "code_2": "H22",
    "code_0": "H00-H59",
    "code_1": "H15-H22"
  },
  {
    "code": "H221",
    "level": 3,
    "description": "Iridociclitis en otras enfermedades clasificadas en otra parte",
    "code_2": "H22",
    "code_0": "H00-H59",
    "code_1": "H15-H22"
  },
  {
    "code": "H228",
    "level": 3,
    "description": "Otros trastornos del iris y del cuerpo ciliar en enfermedades clasificadas en otra parte",
    "code_2": "H22",
    "code_0": "H00-H59",
    "code_1": "H15-H22"
  },
  {
    "code": "H750",
    "level": 3,
    "description": "Mastoiditis en enfermedades infecciosas y parasitarias clasificadas en otra parte",
    "code_2": "H75",
    "code_0": "H60-H95",
    "code_1": "H65-H75"
  },
  {
    "code": "H758",
    "level": 3,
    "description": "Otros trastornos especificados del o\u00eddo medio y de la ap\u00f3fisis mastoides en enfermedades clasificadas en otra parte",
    "code_2": "H75",
    "code_0": "H60-H95",
    "code_1": "H65-H75"
  },
  {
    "code": "H740",
    "level": 3,
    "description": "Timpanosclerosis",
    "code_2": "H74",
    "code_0": "H60-H95",
    "code_1": "H65-H75"
  },
  {
    "code": "H741",
    "level": 3,
    "description": "Enfermedad adhesiva del o\u00eddo medio",
    "code_2": "H74",
    "code_0": "H60-H95",
    "code_1": "H65-H75"
  },
  {
    "code": "H742",
    "level": 3,
    "description": "Discontinuidad y dislocaci\u00f3n de los huesecillos del o\u00eddo",
    "code_2": "H74",
    "code_0": "H60-H95",
    "code_1": "H65-H75"
  },
  {
    "code": "H743",
    "level": 3,
    "description": "Otras anormalidades adquiridas de los huesecillos del o\u00eddo",
    "code_2": "H74",
    "code_0": "H60-H95",
    "code_1": "H65-H75"
  },
  {
    "code": "H744",
    "level": 3,
    "description": "P\u00f3lipo del o\u00eddo medio",
    "code_2": "H74",
    "code_0": "H60-H95",
    "code_1": "H65-H75"
  },
  {
    "code": "H748",
    "level": 3,
    "description": "Otros trastornos especificados del o\u00eddo medio y de la ap\u00f3fisis mastoides",
    "code_2": "H74",
    "code_0": "H60-H95",
    "code_1": "H65-H75"
  },
  {
    "code": "H749",
    "level": 3,
    "description": "Trastorno del o\u00eddo medio y de la ap\u00f3fisis mastoides, no especificado",
    "code_2": "H74",
    "code_0": "H60-H95",
    "code_1": "H65-H75"
  },
  {
    "code": "H730",
    "level": 3,
    "description": "Miringitis aguda",
    "code_2": "H73",
    "code_0": "H60-H95",
    "code_1": "H65-H75"
  },
  {
    "code": "H731",
    "level": 3,
    "description": "Miringitis cr\u00f3nica",
    "code_2": "H73",
    "code_0": "H60-H95",
    "code_1": "H65-H75"
  },
  {
    "code": "H738",
    "level": 3,
    "description": "Otros trastornos especificados de la membrana timp\u00e1nica",
    "code_2": "H73",
    "code_0": "H60-H95",
    "code_1": "H65-H75"
  },
  {
    "code": "H739",
    "level": 3,
    "description": "Trastorno de la membrana timp\u00e1nica, no especificado",
    "code_2": "H73",
    "code_0": "H60-H95",
    "code_1": "H65-H75"
  },
  {
    "code": "M489",
    "level": 4,
    "description": "Espondilopat\u00eda, no especificada",
    "code_3": "M48",
    "code_0": "M00-M99",
    "code_1": "M40-M54",
    "code_2": "M45-M49"
  },
  {
    "code": "H720",
    "level": 3,
    "description": "Perforaci\u00f3n central de la membrana timp\u00e1nica",
    "code_2": "H72",
    "code_0": "H60-H95",
    "code_1": "H65-H75"
  },
  {
    "code": "H721",
    "level": 3,
    "description": "Perforaci\u00f3n \u00e1tica de la membrana timp\u00e1nica",
    "code_2": "H72",
    "code_0": "H60-H95",
    "code_1": "H65-H75"
  },
  {
    "code": "H722",
    "level": 3,
    "description": "Otras perforaciones marginales de la membrana timp\u00e1nica",
    "code_2": "H72",
    "code_0": "H60-H95",
    "code_1": "H65-H75"
  },
  {
    "code": "H728",
    "level": 3,
    "description": "Otras perforaciones de la membrana timp\u00e1nica",
    "code_2": "H72",
    "code_0": "H60-H95",
    "code_1": "H65-H75"
  },
  {
    "code": "H729",
    "level": 3,
    "description": "Perforaci\u00f3n de la membrana timp\u00e1nica, sin otra especificaci\u00f3n",
    "code_2": "H72",
    "code_0": "H60-H95",
    "code_1": "H65-H75"
  },
  {
    "code": "M518",
    "level": 4,
    "description": "Otros trastornos especificados de los discos intervertebrales",
    "code_3": "M51",
    "code_0": "M00-M99",
    "code_1": "M40-M54",
    "code_2": "M50-M54"
  },
  {
    "code": "M519",
    "level": 4,
    "description": "Trastorno de los discos intervertebrales, no especificado",
    "code_3": "M51",
    "code_0": "M00-M99",
    "code_1": "M40-M54",
    "code_2": "M50-M54"
  },
  {
    "code": "H700",
    "level": 3,
    "description": "Mastoiditis aguda",
    "code_2": "H70",
    "code_0": "H60-H95",
    "code_1": "H65-H75"
  },
  {
    "code": "H701",
    "level": 3,
    "description": "Mastoiditis cr\u00f3nica",
    "code_2": "H70",
    "code_0": "H60-H95",
    "code_1": "H65-H75"
  },
  {
    "code": "H702",
    "level": 3,
    "description": "Petrositis",
    "code_2": "H70",
    "code_0": "H60-H95",
    "code_1": "H65-H75"
  },
  {
    "code": "H708",
    "level": 3,
    "description": "Otras mastoiditis y afecciones relacionadas",
    "code_2": "H70",
    "code_0": "H60-H95",
    "code_1": "H65-H75"
  },
  {
    "code": "H709",
    "level": 3,
    "description": "Mastoiditis, no especificada",
    "code_2": "H70",
    "code_0": "H60-H95",
    "code_1": "H65-H75"
  },
  {
    "code": "H690",
    "level": 3,
    "description": "Distensi\u00f3n de la trompa de Eustaquio",
    "code_2": "H69",
    "code_0": "H60-H95",
    "code_1": "H65-H75"
  },
  {
    "code": "H698",
    "level": 3,
    "description": "Otros trastornos especificados de la trompa de Eustaquio",
    "code_2": "H69",
    "code_0": "H60-H95",
    "code_1": "H65-H75"
  },
  {
    "code": "H699",
    "level": 3,
    "description": "Trastorno de la trompa de Eustaquio, no especificado",
    "code_2": "H69",
    "code_0": "H60-H95",
    "code_1": "H65-H75"
  },
  {
    "code": "H680",
    "level": 3,
    "description": "Salpingitis eustaquiana",
    "code_2": "H68",
    "code_0": "H60-H95",
    "code_1": "H65-H75"
  },
  {
    "code": "H681",
    "level": 3,
    "description": "Obstrucci\u00f3n de la trompa de Eustaquio",
    "code_2": "H68",
    "code_0": "H60-H95",
    "code_1": "H65-H75"
  },
  {
    "code": "H670",
    "level": 3,
    "description": "Otitis media en enfermedades bacterianas clasificadas en otra parte",
    "code_2": "H67",
    "code_0": "H60-H95",
    "code_1": "H65-H75"
  },
  {
    "code": "H671",
    "level": 3,
    "description": "Otitis media en enfermedades virales clasificadas en otra parte",
    "code_2": "H67",
    "code_0": "H60-H95",
    "code_1": "H65-H75"
  },
  {
    "code": "H678",
    "level": 3,
    "description": "Otitis media en otras enfermedades clasificadas en otra parte",
    "code_2": "H67",
    "code_0": "H60-H95",
    "code_1": "H65-H75"
  },
  {
    "code": "G410",
    "level": 3,
    "description": "Estado de gran mal epil\u00e9ptico",
    "code_2": "G41",
    "code_0": "G00-G99",
    "code_1": "G40-G47"
  },
  {
    "code": "G411",
    "level": 3,
    "description": "Estado de peque\u00f1o mal epil\u00e9ptico",
    "code_2": "G41",
    "code_0": "G00-G99",
    "code_1": "G40-G47"
  },
  {
    "code": "G412",
    "level": 3,
    "description": "Estado de mal epil\u00e9ptico parcial complejo",
    "code_2": "G41",
    "code_0": "G00-G99",
    "code_1": "G40-G47"
  },
  {
    "code": "G418",
    "level": 3,
    "description": "Otros estados epil\u00e9pticos",
    "code_2": "G41",
    "code_0": "G00-G99",
    "code_1": "G40-G47"
  },
  {
    "code": "G419",
    "level": 3,
    "description": "Estado de mal epil\u00e9ptico de tipo no especificado",
    "code_2": "G41",
    "code_0": "G00-G99",
    "code_1": "G40-G47"
  },
  {
    "code": "G400",
    "level": 3,
    "description": "Epilepsia y s\u00edndromes epil\u00e9pticos idiop\u00e1ticos relacionados con localizaciones (focales) (parciales) y con ataques de inicio localizado",
    "code_2": "G40",
    "code_0": "G00-G99",
    "code_1": "G40-G47"
  },
  {
    "code": "G401",
    "level": 3,
    "description": "Epilepsia y s\u00edndromes epil\u00e9pticos sintom\u00e1ticos relacionados con localizaciones (focales) (parciales) y con ataques parciales simples",
    "code_2": "G40",
    "code_0": "G00-G99",
    "code_1": "G40-G47"
  },
  {
    "code": "G402",
    "level": 3,
    "description": "Epilepsia y s\u00edndromes epil\u00e9pticos sintom\u00e1ticos relacionados con localizaciones (focales) (parciales) y con ataques parciales complejos",
    "code_2": "G40",
    "code_0": "G00-G99",
    "code_1": "G40-G47"
  },
  {
    "code": "G403",
    "level": 3,
    "description": "Epilepsia y s\u00edndromes epil\u00e9pticos idiop\u00e1ticos generalizados",
    "code_2": "G40",
    "code_0": "G00-G99",
    "code_1": "G40-G47"
  },
  {
    "code": "G404",
    "level": 3,
    "description": "Otras epilepsias y s\u00edndromes epil\u00e9pticos generalizados",
    "code_2": "G40",
    "code_0": "G00-G99",
    "code_1": "G40-G47"
  },
  {
    "code": "G405",
    "level": 3,
    "description": "S\u00edndromes epil\u00e9pticos especiales",
    "code_2": "G40",
    "code_0": "G00-G99",
    "code_1": "G40-G47"
  },
  {
    "code": "G406",
    "level": 3,
    "description": "Ataques de gran mal, no especificados (con o sin peque\u00f1o mal)",
    "code_2": "G40",
    "code_0": "G00-G99",
    "code_1": "G40-G47"
  },
  {
    "code": "G407",
    "level": 3,
    "description": "Peque\u00f1o mal, no especificado (sin ataque de gran mal)",
    "code_2": "G40",
    "code_0": "G00-G99",
    "code_1": "G40-G47"
  },
  {
    "code": "G408",
    "level": 3,
    "description": "Otras epilepsias",
    "code_2": "G40",
    "code_0": "G00-G99",
    "code_1": "G40-G47"
  },
  {
    "code": "G409",
    "level": 3,
    "description": "Epilepsia, tipo no especificado",
    "code_2": "G40",
    "code_0": "G00-G99",
    "code_1": "G40-G47"
  },
  {
    "code": "G520",
    "level": 3,
    "description": "Trastornos del nervio olfatorio",
    "code_2": "G52",
    "code_0": "G00-G99",
    "code_1": "G50-G59"
  },
  {
    "code": "G521",
    "level": 3,
    "description": "Trastornos del nervio glosofar\u00edngeo",
    "code_2": "G52",
    "code_0": "G00-G99",
    "code_1": "G50-G59"
  },
  {
    "code": "G522",
    "level": 3,
    "description": "Trastornos del nervio vago",
    "code_2": "G52",
    "code_0": "G00-G99",
    "code_1": "G50-G59"
  },
  {
    "code": "G523",
    "level": 3,
    "description": "Trastornos del nervio hipogloso",
    "code_2": "G52",
    "code_0": "G00-G99",
    "code_1": "G50-G59"
  },
  {
    "code": "G527",
    "level": 3,
    "description": "Trastornos de m\u00faltiples nervios craneales",
    "code_2": "G52",
    "code_0": "G00-G99",
    "code_1": "G50-G59"
  },
  {
    "code": "G528",
    "level": 3,
    "description": "Trastornos de otros nervios craneales especificados",
    "code_2": "G52",
    "code_0": "G00-G99",
    "code_1": "G50-G59"
  },
  {
    "code": "G529",
    "level": 3,
    "description": "Trastorno de nervio craneal, no especificado",
    "code_2": "G52",
    "code_0": "G00-G99",
    "code_1": "G50-G59"
  },
  {
    "code": "G510",
    "level": 3,
    "description": "Par\u00e1lisis de Bell",
    "code_2": "G51",
    "code_0": "G00-G99",
    "code_1": "G50-G59"
  },
  {
    "code": "G511",
    "level": 3,
    "description": "Ganglionitis geniculada",
    "code_2": "G51",
    "code_0": "G00-G99",
    "code_1": "G50-G59"
  },
  {
    "code": "G512",
    "level": 3,
    "description": "S\u00edndrome de Melkersson",
    "code_2": "G51",
    "code_0": "G00-G99",
    "code_1": "G50-G59"
  },
  {
    "code": "G513",
    "level": 3,
    "description": "Espasmo hemifacial cl\u00f3nico",
    "code_2": "G51",
    "code_0": "G00-G99",
    "code_1": "G50-G59"
  },
  {
    "code": "G514",
    "level": 3,
    "description": "Mioquimia facial",
    "code_2": "G51",
    "code_0": "G00-G99",
    "code_1": "G50-G59"
  },
  {
    "code": "G518",
    "level": 3,
    "description": "Otros trastornos del nervio facial",
    "code_2": "G51",
    "code_0": "G00-G99",
    "code_1": "G50-G59"
  },
  {
    "code": "G500",
    "level": 3,
    "description": "Neuralgia del trig\u00e9mino",
    "code_2": "G50",
    "code_0": "G00-G99",
    "code_1": "G50-G59"
  },
  {
    "code": "G501",
    "level": 3,
    "description": "Dolor facial at\u00edpico",
    "code_2": "G50",
    "code_0": "G00-G99",
    "code_1": "G50-G59"
  },
  {
    "code": "G508",
    "level": 3,
    "description": "Otros trastornos del trig\u00e9mino",
    "code_2": "G50",
    "code_0": "G00-G99",
    "code_1": "G50-G59"
  },
  {
    "code": "G509",
    "level": 3,
    "description": "Trastorno del trig\u00e9mino, no especificado",
    "code_2": "G50",
    "code_0": "G00-G99",
    "code_1": "G50-G59"
  },
  {
    "code": "G630",
    "level": 3,
    "description": "Polineuropat\u00eda en enfermedades infecciosas y parasitarias clasificadas en otra parte",
    "code_2": "G63",
    "code_0": "G00-G99",
    "code_1": "G60-G64"
  },
  {
    "code": "G631",
    "level": 3,
    "description": "Polineuropat\u00eda en enfermedad neopl\u00e1sica (C00\u2013D48)",
    "code_2": "G63",
    "code_0": "G00-G99",
    "code_1": "G60-G64"
  },
  {
    "code": "G632",
    "level": 3,
    "description": "Polineuropat\u00eda diab\u00e9tica (E10\u2013E14 con cuarto car\u00e1cter com\u00fan .4)",
    "code_2": "G63",
    "code_0": "G00-G99",
    "code_1": "G60-G64"
  },
  {
    "code": "G633",
    "level": 3,
    "description": "Polineuropat\u00eda en otras enfermedades endocrinas y metab\u00f3licas (E00\u2013E07, E15\u2013E16, E20\u2013E34, E70\u2013E89)",
    "code_2": "G63",
    "code_0": "G00-G99",
    "code_1": "G60-G64"
  },
  {
    "code": "G634",
    "level": 3,
    "description": "Polineuropat\u00eda en deficiencia nutricional (E40\u2013E64)",
    "code_2": "G63",
    "code_0": "G00-G99",
    "code_1": "G60-G64"
  },
  {
    "code": "G635",
    "level": 3,
    "description": "Polineuropat\u00eda en trastornos del tejido conectivo sist\u00e9mico (M30\u2013M35)",
    "code_2": "G63",
    "code_0": "G00-G99",
    "code_1": "G60-G64"
  },
  {
    "code": "G636",
    "level": 3,
    "description": "Polineuropat\u00eda en otros trastornos osteomusculares (M00\u2013M25, M40\u2013M96)",
    "code_2": "G63",
    "code_0": "G00-G99",
    "code_1": "G60-G64"
  },
  {
    "code": "G638",
    "level": 3,
    "description": "Polineuropat\u00eda en otras enfermedades clasificadas en otra parte",
    "code_2": "G63",
    "code_0": "G00-G99",
    "code_1": "G60-G64"
  },
  {
    "code": "G620",
    "level": 3,
    "description": "Polineuropat\u00eda inducida por drogas",
    "code_2": "G62",
    "code_0": "G00-G99",
    "code_1": "G60-G64"
  },
  {
    "code": "G621",
    "level": 3,
    "description": "Polineuropat\u00eda alcoh\u00f3lica",
    "code_2": "G62",
    "code_0": "G00-G99",
    "code_1": "G60-G64"
  },
  {
    "code": "G622",
    "level": 3,
    "description": "Polineuropat\u00eda debida a otro agente t\u00f3xico",
    "code_2": "G62",
    "code_0": "G00-G99",
    "code_1": "G60-G64"
  },
  {
    "code": "G628",
    "level": 3,
    "description": "Otras polineuropat\u00edas especificadas",
    "code_2": "G62",
    "code_0": "G00-G99",
    "code_1": "G60-G64"
  },
  {
    "code": "G629",
    "level": 3,
    "description": "Polineuropat\u00eda, no especificada",
    "code_2": "G62",
    "code_0": "G00-G99",
    "code_1": "G60-G64"
  },
  {
    "code": "G610",
    "level": 3,
    "description": "S\u00edndrome de Guillain\u2013Barr\u00e9",
    "code_2": "G61",
    "code_0": "G00-G99",
    "code_1": "G60-G64"
  },
  {
    "code": "G611",
    "level": 3,
    "description": "Neuropat\u00eda al suero",
    "code_2": "G61",
    "code_0": "G00-G99",
    "code_1": "G60-G64"
  },
  {
    "code": "G618",
    "level": 3,
    "description": "Otras polineuropat\u00edas inflamatorias",
    "code_2": "G61",
    "code_0": "G00-G99",
    "code_1": "G60-G64"
  },
  {
    "code": "G619",
    "level": 3,
    "description": "Polineuropat\u00eda inflamatoria, no especificada",
    "code_2": "G61",
    "code_0": "G00-G99",
    "code_1": "G60-G64"
  },
  {
    "code": "G600",
    "level": 3,
    "description": "Neuropat\u00eda hereditaria motora y sensorial",
    "code_2": "G60",
    "code_0": "G00-G99",
    "code_1": "G60-G64"
  },
  {
    "code": "G601",
    "level": 3,
    "description": "Enfermedad de Refsum",
    "code_2": "G60",
    "code_0": "G00-G99",
    "code_1": "G60-G64"
  },
  {
    "code": "G602",
    "level": 3,
    "description": "Neuropat\u00eda asociada con ataxia hereditaria",
    "code_2": "G60",
    "code_0": "G00-G99",
    "code_1": "G60-G64"
  },
  {
    "code": "G603",
    "level": 3,
    "description": "Neuropat\u00eda progresiva idiop\u00e1tica",
    "code_2": "G60",
    "code_0": "G00-G99",
    "code_1": "G60-G64"
  },
  {
    "code": "G608",
    "level": 3,
    "description": "Otras neuropat\u00edas hereditarias e idiop\u00e1ticas",
    "code_2": "G60",
    "code_0": "G00-G99",
    "code_1": "G60-G64"
  },
  {
    "code": "G609",
    "level": 3,
    "description": "Neuropat\u00eda hereditaria e idiop\u00e1tica, sin otra especificaci\u00f3n",
    "diagnostico": "",
    "code_2": "G60",
    "code_0": "G00-G99",
    "code_1": "G60-G64"
  },
  {
    "code": "G720",
    "level": 3,
    "description": "Miopat\u00eda inducida por drogas",
    "code_2": "G72",
    "code_0": "G00-G99",
    "code_1": "G70-G73"
  },
  {
    "code": "G721",
    "level": 3,
    "description": "Miopat\u00eda alcoh\u00f3lica",
    "code_2": "G72",
    "code_0": "G00-G99",
    "code_1": "G70-G73"
  },
  {
    "code": "G722",
    "level": 3,
    "description": "Miopat\u00eda debida a otros agentes t\u00f3xicos",
    "code_2": "G72",
    "code_0": "G00-G99",
    "code_1": "G70-G73"
  },
  {
    "code": "G723",
    "level": 3,
    "description": "Par\u00e1lisis peri\u00f3dica",
    "code_2": "G72",
    "code_0": "G00-G99",
    "code_1": "G70-G73"
  },
  {
    "code": "G724",
    "level": 3,
    "description": "Miopat\u00eda inflamatoria, no clasificada en otra parte",
    "code_2": "G72",
    "code_0": "G00-G99",
    "code_1": "G70-G73"
  },
  {
    "code": "G728",
    "level": 3,
    "description": "Otras miopat\u00edas especificadas",
    "code_2": "G72",
    "code_0": "G00-G99",
    "code_1": "G70-G73"
  },
  {
    "code": "G729",
    "level": 3,
    "description": "Miopat\u00eda, no especificada",
    "code_2": "G72",
    "code_0": "G00-G99",
    "code_1": "G70-G73"
  },
  {
    "code": "M256",
    "level": 4,
    "description": "Rigidez articular, no clasificada en otra parte",
    "code_3": "M25",
    "code_0": "M00-M99",
    "code_1": "M00-M25",
    "code_2": "M20-M25"
  },
  {
    "code": "M257",
    "level": 4,
    "description": "Osteofito",
    "code_3": "M25",
    "code_0": "M00-M99",
    "code_1": "M00-M25",
    "code_2": "M20-M25"
  },
  {
    "code": "M258",
    "level": 4,
    "description": "Otros trastornos articulares especificados",
    "code_3": "M25",
    "code_0": "M00-M99",
    "code_1": "M00-M25",
    "code_2": "M20-M25"
  },
  {
    "code": "M259",
    "level": 4,
    "description": "Trastorno articular, no especificado",
    "code_3": "M25",
    "code_0": "M00-M99",
    "code_1": "M00-M25",
    "code_2": "M20-M25"
  },
  {
    "code": "M248",
    "level": 4,
    "description": "Otras lesiones articulares espec\u00edficas, no clasificadas en otra parte",
    "code_3": "M24",
    "code_0": "M00-M99",
    "code_1": "M00-M25",
    "code_2": "M20-M25"
  },
  {
    "code": "M249",
    "level": 4,
    "description": "Desarreglo articular, no especificado",
    "code_3": "M24",
    "code_0": "M00-M99",
    "code_1": "M00-M25",
    "code_2": "M20-M25"
  }
]